{
  "n_strands": 7,
  "n_strand_crossings": 89,
  "n_components": 1,
  "n_crossings": 94,
  "n_conn_visits": [
    188
  ],
  "visits": [
    [163, 2],
    [28, 2],
    [165, 3],
    [30, 3],
    [117, 1],
    [168, 2],
    [169, 3],
    [94, 1],
    [37, 1],
    [38, 0],
    [119, 3],
    [120, 1],
    [97, 0],
    [122, 0],
    [123, 1],
    [98, 1],
    [71, 1],
    [102, 0],
    [157, 1],
    [78, 3],
    [159, 3],
    [130, 3],
    [187, 2],
    [162, 2],
    [135, 2],
    [54, 2],
    [55, 0],
    [136, 3],
    [1, 0],
    [164, 3],
    [3, 1],
    [116, 2],
    [167, 2],
    [92, 1],
    [63, 1],
    [64, 3],
    [171, 3],
    [8, 3],
    [9, 2],
    [148, 2],
    [173, 1],
    [66, 1],
    [153, 0],
    [178, 0],
    [69, 3],
    [70, 1],
    [155, 1],
    [180, 1],
    [105, 0],
    [182, 3],
    [183, 1],
    [106, 2],
    [107, 3],
    [82, 0],
    [25, 0],
    [26, 2],
    [109, 1],
    [110, 0],
    [111, 1],
    [84, 1],
    [87, 3],
    [88, 1],
    [145, 3],
    [34, 3],
    [35, 1],
    [146, 1],
    [41, 3],
    [150, 3],
    [175, 0],
    [44, 1],
    [45, 3],
    [16, 3],
    [101, 3],
    [126, 0],
    [127, 1],
    [128, 3],
    [129, 2],
    [158, 1],
    [19, 1],
    [184, 1],
    [133, 3],
    [134, 1],
    [53, 2],
    [108, 1],
    [59, 3],
    [138, 3],
    [139, 1],
    [60, 1],
    [61, 3],
    [142, 0],
    [143, 2],
    [144, 3],
    [33, 3],
    [170, 3],
    [7, 3],
    [118, 3],
    [121, 1],
    [12, 2],
    [15, 3],
    [124, 0],
    [125, 1],
    [72, 1],
    [17, 2],
    [156, 2],
    [181, 1],
    [48, 2],
    [51, 0],
    [52, 1],
    [83, 3],
    [56, 3],
    [57, 2],
    [58, 3],
    [137, 0],
    [140, 1],
    [141, 3],
    [166, 3],
    [31, 0],
    [4, 3],
    [95, 1],
    [10, 1],
    [11, 3],
    [96, 3],
    [13, 2],
    [14, 3],
    [99, 2],
    [100, 3],
    [73, 2],
    [74, 3],
    [75, 1],
    [76, 0],
    [21, 1],
    [186, 1],
    [161, 2],
    [80, 1],
    [81, 3],
    [24, 0],
    [27, 1],
    [112, 2],
    [85, 1],
    [86, 3],
    [113, 3],
    [114, 1],
    [89, 2],
    [90, 0],
    [91, 1],
    [62, 1],
    [65, 3],
    [172, 3],
    [39, 0],
    [174, 2],
    [67, 1],
    [176, 0],
    [177, 1],
    [42, 2],
    [179, 3],
    [46, 3],
    [103, 0],
    [18, 3],
    [77, 3],
    [20, 1],
    [185, 1],
    [132, 0],
    [23, 0],
    [0, 0],
    [29, 1],
    [2, 1],
    [115, 1],
    [32, 0],
    [5, 0],
    [6, 1],
    [93, 1],
    [36, 1],
    [147, 1],
    [40, 3],
    [149, 0],
    [68, 2],
    [151, 2],
    [152, 3],
    [43, 2],
    [154, 1],
    [47, 3],
    [104, 3],
    [49, 1],
    [50, 3],
    [79, 3],
    [160, 3],
    [131, 3],
    [22, 0]
  ]
}