{
  "n_strands": 17,
  "n_strand_crossings": 267,
  "n_components": 1,
  "n_crossings": 274,
  "n_conn_visits": [
    548
  ],
  "visits": [
    [417, 2],
    [418, 3],
    [419, 1],
    [520, 1],
    [29, 2],
    [384, 2],
    [39, 0],
    [356, 2],
    [357, 3],
    [392, 0],
    [359, 2],
    [42, 1],
    [43, 0],
    [362, 3],
    [363, 1],
    [364, 0],
    [365, 1],
    [398, 1],
    [429, 0],
    [404, 3],
    [371, 3],
    [438, 1],
    [537, 3],
    [440, 3],
    [545, 1],
    [546, 0],
    [547, 1],
    [416, 1],
    [519, 1],
    [4, 0],
    [385, 1],
    [522, 0],
    [523, 2],
    [524, 0],
    [421, 0],
    [422, 2],
    [525, 2],
    [526, 3],
    [527, 2],
    [6, 2],
    [355, 2],
    [394, 0],
    [11, 3],
    [12, 2],
    [397, 2],
    [496, 1],
    [497, 3],
    [498, 1],
    [261, 2],
    [262, 0],
    [263, 2],
    [264, 0],
    [501, 3],
    [432, 0],
    [433, 2],
    [434, 0],
    [435, 2],
    [506, 1],
    [471, 2],
    [206, 1],
    [207, 3],
    [336, 2],
    [337, 0],
    [338, 2],
    [339, 0],
    [188, 2],
    [341, 1],
    [242, 2],
    [243, 3],
    [244, 1],
    [107, 1],
    [214, 2],
    [217, 3],
    [324, 2],
    [219, 1],
    [166, 1],
    [287, 2],
    [288, 0],
    [167, 0],
    [168, 1],
    [169, 3],
    [170, 1],
    [295, 1],
    [298, 0],
    [175, 3],
    [124, 3],
    [125, 2],
    [126, 3],
    [227, 3],
    [228, 2],
    [303, 2],
    [304, 3],
    [229, 0],
    [230, 1],
    [231, 3],
    [232, 2],
    [329, 0],
    [308, 1],
    [309, 3],
    [270, 3],
    [235, 3],
    [334, 1],
    [273, 1],
    [182, 2],
    [275, 3],
    [240, 1],
    [213, 0],
    [70, 3],
    [215, 2],
    [216, 3],
    [249, 0],
    [250, 1],
    [251, 3],
    [252, 2],
    [325, 1],
    [220, 2],
    [171, 2],
    [172, 0],
    [221, 0],
    [222, 1],
    [223, 0],
    [224, 1],
    [225, 0],
    [226, 2],
    [85, 1],
    [86, 0],
    [87, 1],
    [302, 2],
    [305, 3],
    [306, 1],
    [177, 2],
    [152, 2],
    [153, 0],
    [154, 2],
    [157, 3],
    [316, 3],
    [317, 1],
    [158, 2],
    [281, 0],
    [282, 1],
    [283, 3],
    [162, 3],
    [285, 1],
    [164, 2],
    [289, 0],
    [290, 2],
    [291, 3],
    [292, 2],
    [293, 3],
    [294, 1],
    [299, 0],
    [300, 1],
    [131, 0],
    [132, 2],
    [133, 0],
    [314, 0],
    [315, 2],
    [134, 1],
    [137, 0],
    [280, 0],
    [321, 0],
    [322, 2],
    [141, 1],
    [284, 1],
    [143, 0],
    [286, 0],
    [75, 3],
    [78, 2],
    [79, 3],
    [80, 1],
    [81, 3],
    [116, 0],
    [117, 2],
    [296, 1],
    [297, 3],
    [84, 1],
    [301, 1],
    [130, 0],
    [311, 3],
    [312, 1],
    [313, 3],
    [238, 3],
    [103, 0],
    [274, 0],
    [209, 3],
    [210, 1],
    [211, 3],
    [340, 0],
    [65, 0],
    [342, 1],
    [343, 0],
    [344, 1],
    [245, 1],
    [246, 3],
    [247, 2],
    [248, 0],
    [349, 0],
    [486, 0],
    [455, 0],
    [354, 2],
    [491, 2],
    [258, 1],
    [463, 1],
    [326, 2],
    [327, 3],
    [268, 0],
    [59, 3],
    [60, 1],
    [335, 1],
    [184, 1],
    [185, 3],
    [186, 1],
    [241, 2],
    [106, 2],
    [71, 0],
    [108, 0],
    [109, 1],
    [72, 1],
    [323, 1],
    [74, 3],
    [115, 0],
    [118, 2],
    [119, 3],
    [120, 2],
    [121, 3],
    [122, 2],
    [123, 0],
    [88, 1],
    [89, 0],
    [92, 2],
    [93, 3],
    [94, 1],
    [95, 0],
    [328, 0],
    [269, 3],
    [100, 1],
    [333, 2],
    [272, 2],
    [181, 1],
    [276, 3],
    [105, 3],
    [212, 0],
    [67, 0],
    [68, 1],
    [69, 3],
    [192, 3],
    [193, 1],
    [194, 0],
    [195, 2],
    [110, 2],
    [111, 3],
    [112, 1],
    [113, 0],
    [350, 0],
    [351, 2],
    [458, 3],
    [459, 2],
    [462, 3],
    [201, 3],
    [464, 2],
    [467, 3],
    [48, 0],
    [49, 2],
    [50, 0],
    [51, 2],
    [502, 3],
    [469, 1],
    [504, 1],
    [205, 2],
    [234, 1],
    [99, 1],
    [332, 1],
    [237, 0],
    [102, 3],
    [183, 2],
    [104, 1],
    [239, 1],
    [318, 1],
    [319, 3],
    [320, 2],
    [159, 2],
    [138, 2],
    [139, 3],
    [140, 1],
    [163, 3],
    [142, 3],
    [165, 2],
    [76, 0],
    [77, 2],
    [144, 2],
    [145, 0],
    [146, 1],
    [147, 0],
    [148, 1],
    [149, 3],
    [82, 3],
    [173, 3],
    [174, 1],
    [83, 2],
    [150, 2],
    [151, 3],
    [176, 3],
    [127, 0],
    [90, 0],
    [91, 1],
    [128, 1],
    [129, 3],
    [330, 0],
    [97, 3],
    [98, 1],
    [331, 2],
    [178, 1],
    [179, 3],
    [180, 1],
    [155, 2],
    [156, 0],
    [135, 1],
    [136, 3],
    [277, 3],
    [278, 1],
    [279, 0],
    [160, 2],
    [161, 0],
    [218, 3],
    [73, 0],
    [114, 3],
    [203, 0],
    [204, 1],
    [233, 2],
    [96, 2],
    [307, 2],
    [310, 0],
    [271, 3],
    [236, 0],
    [101, 3],
    [208, 3],
    [61, 0],
    [62, 2],
    [63, 0],
    [64, 2],
    [187, 2],
    [66, 3],
    [189, 3],
    [190, 2],
    [191, 3],
    [452, 3],
    [483, 3],
    [484, 1],
    [453, 1],
    [196, 2],
    [253, 2],
    [254, 0],
    [457, 3],
    [488, 3],
    [199, 0],
    [40, 0],
    [7, 0],
    [8, 1],
    [393, 3],
    [10, 0],
    [531, 3],
    [532, 1],
    [13, 1],
    [14, 3],
    [15, 2],
    [16, 3],
    [427, 0],
    [400, 2],
    [401, 3],
    [402, 1],
    [403, 0],
    [20, 1],
    [437, 1],
    [406, 2],
    [473, 1],
    [474, 3],
    [477, 2],
    [478, 3],
    [479, 1],
    [480, 3],
    [411, 0],
    [444, 0],
    [415, 2],
    [518, 2],
    [5, 0],
    [30, 3],
    [521, 0],
    [420, 3],
    [423, 1],
    [528, 1],
    [529, 3],
    [530, 2],
    [9, 2],
    [358, 1],
    [41, 2],
    [492, 2],
    [493, 0],
    [44, 0],
    [17, 3],
    [428, 3],
    [367, 0],
    [368, 1],
    [369, 3],
    [370, 2],
    [19, 1],
    [436, 2],
    [373, 0],
    [538, 3],
    [539, 1],
    [540, 3],
    [541, 2],
    [380, 2],
    [511, 1],
    [514, 3],
    [447, 3],
    [382, 0],
    [27, 3],
    [0, 0],
    [1, 1],
    [2, 3],
    [387, 1],
    [34, 2],
    [35, 0],
    [388, 3],
    [533, 1],
    [534, 0],
    [535, 1],
    [366, 2],
    [399, 1],
    [18, 2],
    [499, 1],
    [500, 0],
    [53, 2],
    [54, 0],
    [55, 2],
    [56, 0],
    [405, 0],
    [372, 3],
    [21, 3],
    [536, 3],
    [23, 1],
    [542, 1],
    [543, 3],
    [544, 1],
    [381, 2],
    [512, 1],
    [513, 0],
    [414, 1],
    [515, 1],
    [516, 3],
    [517, 1],
    [482, 1],
    [345, 1],
    [348, 3],
    [485, 0],
    [198, 2],
    [487, 2],
    [352, 1],
    [255, 1],
    [256, 0],
    [489, 3],
    [490, 1],
    [257, 1],
    [202, 3],
    [259, 0],
    [494, 3],
    [495, 1],
    [260, 1],
    [503, 3],
    [266, 3],
    [505, 2],
    [58, 0],
    [507, 0],
    [374, 3],
    [375, 1],
    [508, 2],
    [509, 3],
    [376, 0],
    [377, 1],
    [378, 3],
    [379, 1],
    [510, 1],
    [451, 3],
    [346, 1],
    [347, 3],
    [454, 2],
    [197, 2],
    [456, 0],
    [353, 1],
    [460, 1],
    [461, 3],
    [200, 0],
    [395, 0],
    [396, 2],
    [465, 1],
    [466, 3],
    [45, 3],
    [46, 1],
    [47, 3],
    [430, 3],
    [431, 2],
    [52, 1],
    [265, 1],
    [468, 1],
    [267, 3],
    [470, 0],
    [57, 3],
    [472, 2],
    [475, 0],
    [476, 1],
    [481, 3],
    [412, 3],
    [445, 3],
    [446, 2],
    [413, 1],
    [448, 3],
    [449, 1],
    [450, 3],
    [383, 0],
    [28, 3],
    [3, 3],
    [386, 2],
    [31, 2],
    [32, 0],
    [33, 2],
    [36, 0],
    [37, 1],
    [38, 0],
    [389, 3],
    [390, 1],
    [391, 0],
    [360, 1],
    [361, 3],
    [424, 3],
    [425, 2],
    [426, 3],
    [439, 1],
    [22, 1],
    [407, 1],
    [408, 3],
    [409, 1],
    [410, 0],
    [441, 3],
    [442, 1],
    [443, 3],
    [24, 3],
    [25, 2],
    [26, 3]
  ]
}