{
  "n_strands": 20,
  "n_strand_crossings": 32,
  "n_components": 1,
  "n_crossings": 39,
  "n_conn_visits": [
    78
  ],
  "visits": [
    [75, 1],
    [76, 0],
    [77, 1],
    [74, 1],
    [73, 1],
    [70, 1],
    [71, 0],
    [72, 1],
    [69, 1],
    [68, 1],
    [53, 2],
    [62, 1],
    [55, 3],
    [56, 2],
    [49, 1],
    [50, 3],
    [51, 2],
    [48, 1],
    [47, 1],
    [44, 2],
    [41, 2],
    [40, 1],
    [37, 1],
    [32, 1],
    [29, 2],
    [28, 2],
    [27, 1],
    [26, 3],
    [25, 0],
    [24, 0],
    [35, 3],
    [36, 1],
    [23, 3],
    [38, 0],
    [39, 2],
    [30, 1],
    [31, 3],
    [22, 3],
    [33, 2],
    [34, 0],
    [21, 3],
    [20, 0],
    [45, 3],
    [46, 2],
    [19, 0],
    [42, 1],
    [43, 0],
    [18, 3],
    [17, 3],
    [14, 3],
    [15, 1],
    [16, 0],
    [61, 0],
    [10, 0],
    [63, 1],
    [12, 1],
    [13, 0],
    [64, 3],
    [65, 2],
    [66, 3],
    [67, 1],
    [52, 2],
    [11, 3],
    [54, 3],
    [57, 1],
    [58, 0],
    [59, 1],
    [60, 3],
    [9, 3],
    [8, 3],
    [5, 3],
    [6, 2],
    [7, 3],
    [4, 3],
    [3, 3],
    [0, 3],
    [1, 2],
    [2, 3]
  ]
}