{
  "n_strands": 8,
  "n_strand_crossings": 67,
  "n_components": 1,
  "n_crossings": 71,
  "n_conn_visits": [
    142
  ],
  "visits": [
    [27, 2],
    [28, 0],
    [31, 1],
    [32, 3],
    [19, 1],
    [20, 3],
    [21, 1],
    [138, 1],
    [139, 3],
    [140, 1],
    [103, 2],
    [82, 2],
    [41, 2],
    [62, 1],
    [47, 3],
    [110, 0],
    [69, 3],
    [94, 0],
    [33, 0],
    [4, 3],
    [5, 1],
    [6, 3],
    [141, 2],
    [106, 2],
    [107, 0],
    [90, 1],
    [91, 3],
    [0, 0],
    [1, 2],
    [92, 1],
    [93, 3],
    [2, 3],
    [3, 1],
    [18, 2],
    [117, 2],
    [134, 2],
    [135, 0],
    [118, 0],
    [137, 1],
    [80, 2],
    [101, 2],
    [12, 0],
    [83, 0],
    [104, 0],
    [105, 2],
    [84, 2],
    [63, 2],
    [14, 1],
    [127, 2],
    [130, 3],
    [113, 0],
    [114, 1],
    [131, 1],
    [72, 0],
    [121, 3],
    [74, 2],
    [75, 3],
    [98, 0],
    [79, 2],
    [100, 2],
    [125, 2],
    [126, 0],
    [13, 3],
    [46, 0],
    [85, 0],
    [86, 1],
    [87, 0],
    [88, 2],
    [109, 3],
    [16, 1],
    [115, 2],
    [132, 2],
    [53, 2],
    [122, 3],
    [55, 0],
    [56, 1],
    [123, 1],
    [124, 0],
    [99, 3],
    [58, 0],
    [39, 0],
    [102, 1],
    [11, 0],
    [42, 2],
    [45, 0],
    [64, 2],
    [65, 3],
    [66, 2],
    [67, 0],
    [108, 3],
    [25, 3],
    [26, 1],
    [29, 3],
    [30, 1],
    [17, 2],
    [116, 1],
    [133, 2],
    [120, 0],
    [57, 2],
    [78, 1],
    [59, 0],
    [40, 0],
    [81, 3],
    [10, 0],
    [43, 2],
    [44, 0],
    [23, 0],
    [24, 2],
    [89, 1],
    [68, 1],
    [15, 2],
    [128, 2],
    [129, 3],
    [50, 2],
    [51, 3],
    [70, 0],
    [95, 3],
    [34, 0],
    [37, 2],
    [136, 2],
    [97, 2],
    [54, 1],
    [73, 1],
    [76, 3],
    [77, 2],
    [60, 0],
    [61, 2],
    [48, 0],
    [111, 0],
    [112, 1],
    [49, 1],
    [52, 3],
    [71, 0],
    [96, 0],
    [35, 0],
    [36, 2],
    [119, 0],
    [38, 3],
    [7, 3],
    [8, 1],
    [9, 3],
    [22, 0]
  ]
}