{
  "n_strands": 3,
  "n_strand_crossings": 32,
  "n_components": 1,
  "n_crossings": 32,
  "n_conn_visits": [
    64
  ],
  "visits": [
    [41, 2],
    [42, 3],
    [47, 2],
    [48, 0],
    [49, 1],
    [50, 0],
    [27, 1],
    [52, 2],
    [53, 0],
    [54, 2],
    [29, 0],
    [30, 1],
    [31, 0],
    [32, 1],
    [33, 3],
    [34, 2],
    [37, 0],
    [58, 3],
    [59, 2],
    [60, 0],
    [63, 1],
    [40, 1],
    [43, 3],
    [44, 1],
    [45, 0],
    [46, 2],
    [51, 3],
    [6, 3],
    [55, 2],
    [10, 2],
    [11, 3],
    [12, 2],
    [13, 3],
    [14, 1],
    [15, 0],
    [56, 0],
    [57, 1],
    [16, 2],
    [61, 0],
    [62, 2],
    [21, 3],
    [0, 0],
    [1, 1],
    [22, 1],
    [23, 3],
    [24, 2],
    [25, 0],
    [2, 0],
    [3, 2],
    [4, 3],
    [5, 2],
    [26, 1],
    [7, 0],
    [8, 2],
    [9, 0],
    [28, 0],
    [35, 2],
    [36, 3],
    [17, 1],
    [18, 0],
    [19, 2],
    [38, 2],
    [39, 0],
    [20, 3]
  ]
}