{
  "n_strands": 12,
  "n_strand_crossings": 49,
  "n_components": 1,
  "n_crossings": 51,
  "n_conn_visits": [
    102
  ],
  "visits": [
    [99, 2],
    [12, 2],
    [89, 1],
    [14, 3],
    [91, 0],
    [92, 2],
    [19, 1],
    [20, 0],
    [95, 0],
    [34, 2],
    [97, 2],
    [36, 3],
    [1, 0],
    [90, 2],
    [3, 1],
    [26, 2],
    [27, 3],
    [28, 2],
    [29, 3],
    [6, 3],
    [7, 2],
    [32, 2],
    [79, 2],
    [86, 2],
    [81, 0],
    [38, 0],
    [15, 0],
    [16, 1],
    [17, 0],
    [18, 1],
    [77, 1],
    [78, 3],
    [21, 0],
    [96, 0],
    [9, 0],
    [98, 2],
    [11, 1],
    [88, 2],
    [25, 2],
    [82, 1],
    [73, 1],
    [56, 1],
    [57, 0],
    [58, 2],
    [69, 1],
    [64, 1],
    [65, 0],
    [70, 3],
    [59, 3],
    [60, 2],
    [71, 1],
    [54, 2],
    [67, 2],
    [66, 3],
    [51, 0],
    [62, 3],
    [41, 3],
    [42, 2],
    [43, 0],
    [48, 1],
    [49, 0],
    [72, 2],
    [55, 1],
    [68, 1],
    [45, 3],
    [46, 2],
    [53, 1],
    [52, 0],
    [63, 3],
    [44, 3],
    [47, 1],
    [50, 3],
    [61, 0],
    [40, 3],
    [83, 3],
    [84, 1],
    [85, 3],
    [30, 3],
    [31, 1],
    [22, 0],
    [87, 1],
    [24, 2],
    [39, 3],
    [74, 1],
    [75, 3],
    [76, 1],
    [23, 0],
    [80, 3],
    [37, 0],
    [2, 3],
    [13, 0],
    [4, 2],
    [5, 0],
    [100, 3],
    [101, 2],
    [8, 2],
    [33, 2],
    [10, 0],
    [35, 0],
    [0, 0],
    [93, 1],
    [94, 0]
  ]
}