{
  "n_strands": 22,
  "n_strand_crossings": 50,
  "n_components": 1,
  "n_crossings": 57,
  "n_conn_visits": [
    114
  ],
  "visits": [
    [5, 2],
    [6, 0],
    [113, 2],
    [102, 1],
    [103, 3],
    [0, 0],
    [1, 2],
    [112, 2],
    [107, 1],
    [108, 0],
    [109, 1],
    [100, 1],
    [91, 1],
    [94, 1],
    [95, 0],
    [96, 1],
    [83, 1],
    [84, 3],
    [89, 2],
    [86, 2],
    [81, 2],
    [78, 1],
    [25, 1],
    [76, 1],
    [29, 0],
    [22, 3],
    [79, 0],
    [80, 2],
    [77, 1],
    [24, 2],
    [67, 2],
    [74, 1],
    [69, 0],
    [70, 2],
    [71, 3],
    [72, 1],
    [65, 1],
    [62, 2],
    [63, 3],
    [64, 2],
    [61, 1],
    [46, 1],
    [49, 1],
    [56, 1],
    [53, 3],
    [48, 3],
    [41, 3],
    [60, 1],
    [45, 1],
    [42, 3],
    [57, 2],
    [58, 0],
    [59, 1],
    [44, 1],
    [55, 2],
    [54, 0],
    [43, 3],
    [50, 0],
    [51, 2],
    [52, 3],
    [47, 3],
    [40, 3],
    [37, 0],
    [38, 1],
    [39, 0],
    [36, 3],
    [73, 0],
    [30, 0],
    [75, 2],
    [32, 2],
    [33, 0],
    [34, 1],
    [35, 3],
    [66, 2],
    [31, 3],
    [68, 0],
    [23, 3],
    [28, 3],
    [21, 3],
    [26, 2],
    [27, 0],
    [20, 0],
    [87, 3],
    [16, 3],
    [17, 1],
    [88, 1],
    [19, 0],
    [82, 1],
    [85, 3],
    [18, 0],
    [93, 3],
    [12, 3],
    [97, 1],
    [90, 1],
    [13, 3],
    [14, 2],
    [15, 3],
    [92, 3],
    [105, 0],
    [106, 1],
    [11, 3],
    [110, 3],
    [3, 3],
    [4, 1],
    [111, 1],
    [98, 2],
    [99, 3],
    [8, 3],
    [9, 2],
    [10, 3],
    [101, 1],
    [104, 3],
    [7, 0],
    [2, 0]
  ]
}