{
  "n_strands": 11,
  "n_strand_crossings": 52,
  "n_components": 1,
  "n_crossings": 56,
  "n_conn_visits": [
    112
  ],
  "visits": [
    [105, 2],
    [90, 2],
    [91, 0],
    [106, 3],
    [95, 1],
    [108, 1],
    [97, 3],
    [98, 1],
    [99, 3],
    [102, 2],
    [103, 3],
    [110, 0],
    [111, 1],
    [104, 2],
    [87, 2],
    [88, 3],
    [89, 1],
    [24, 2],
    [25, 0],
    [92, 3],
    [93, 1],
    [84, 1],
    [77, 2],
    [78, 0],
    [17, 0],
    [18, 2],
    [79, 1],
    [80, 0],
    [83, 2],
    [76, 1],
    [57, 1],
    [58, 3],
    [81, 0],
    [82, 2],
    [69, 2],
    [70, 0],
    [71, 2],
    [72, 0],
    [75, 1],
    [56, 2],
    [51, 1],
    [64, 1],
    [65, 3],
    [66, 1],
    [61, 0],
    [54, 3],
    [73, 3],
    [74, 2],
    [55, 1],
    [62, 1],
    [63, 3],
    [40, 3],
    [59, 3],
    [68, 2],
    [45, 1],
    [48, 3],
    [39, 0],
    [30, 3],
    [31, 1],
    [52, 1],
    [67, 1],
    [44, 2],
    [49, 3],
    [50, 1],
    [41, 3],
    [42, 1],
    [43, 3],
    [60, 3],
    [53, 0],
    [34, 0],
    [35, 2],
    [36, 0],
    [37, 2],
    [46, 1],
    [47, 0],
    [38, 3],
    [29, 3],
    [22, 0],
    [23, 2],
    [26, 3],
    [27, 2],
    [32, 2],
    [33, 0],
    [28, 0],
    [21, 3],
    [100, 3],
    [101, 1],
    [14, 0],
    [15, 1],
    [16, 3],
    [1, 0],
    [2, 2],
    [19, 1],
    [20, 3],
    [107, 3],
    [4, 3],
    [109, 1],
    [6, 1],
    [7, 3],
    [8, 1],
    [85, 1],
    [86, 3],
    [9, 0],
    [10, 1],
    [13, 0],
    [0, 0],
    [3, 1],
    [94, 1],
    [5, 3],
    [96, 3],
    [11, 2],
    [12, 3]
  ]
}