{
  "n_strands": 19,
  "n_strand_crossings": 236,
  "n_components": 1,
  "n_crossings": 242,
  "n_conn_visits": [
    484
  ],
  "visits": [
    [115, 1],
    [116, 0],
    [121, 1],
    [122, 0],
    [123, 2],
    [124, 0],
    [125, 1],
    [446, 1],
    [447, 0],
    [448, 1],
    [449, 3],
    [126, 3],
    [451, 1],
    [452, 0],
    [45, 2],
    [46, 0],
    [47, 2],
    [48, 3],
    [481, 2],
    [54, 2],
    [55, 3],
    [56, 2],
    [57, 0],
    [482, 3],
    [483, 2],
    [114, 1],
    [59, 1],
    [464, 1],
    [465, 3],
    [118, 3],
    [119, 1],
    [466, 1],
    [421, 1],
    [442, 2],
    [427, 0],
    [66, 3],
    [471, 3],
    [472, 1],
    [473, 3],
    [474, 1],
    [431, 1],
    [432, 0],
    [475, 0],
    [128, 0],
    [453, 3],
    [14, 0],
    [15, 2],
    [16, 0],
    [17, 1],
    [480, 1],
    [457, 1],
    [458, 0],
    [459, 2],
    [460, 0],
    [19, 0],
    [20, 1],
    [21, 0],
    [22, 2],
    [113, 1],
    [26, 3],
    [117, 0],
    [120, 2],
    [467, 2],
    [422, 1],
    [425, 0],
    [444, 2],
    [35, 1],
    [428, 2],
    [429, 3],
    [430, 1],
    [99, 1],
    [408, 1],
    [411, 3],
    [106, 0],
    [107, 2],
    [138, 3],
    [139, 2],
    [140, 0],
    [419, 2],
    [396, 2],
    [295, 2],
    [342, 1],
    [297, 3],
    [298, 1],
    [147, 1],
    [320, 1],
    [349, 0],
    [322, 0],
    [323, 1],
    [326, 3],
    [155, 0],
    [304, 3],
    [403, 0],
    [404, 1],
    [405, 3],
    [308, 2],
    [309, 0],
    [310, 2],
    [311, 0],
    [70, 3],
    [409, 1],
    [410, 0],
    [433, 0],
    [134, 3],
    [135, 2],
    [434, 2],
    [73, 2],
    [74, 0],
    [137, 3],
    [436, 0],
    [437, 2],
    [438, 0],
    [461, 3],
    [58, 3],
    [25, 3],
    [0, 3],
    [1, 2],
    [60, 2],
    [29, 1],
    [30, 3],
    [61, 0],
    [2, 3],
    [3, 2],
    [4, 0],
    [5, 2],
    [6, 3],
    [11, 1],
    [450, 1],
    [43, 2],
    [476, 1],
    [477, 0],
    [478, 2],
    [455, 0],
    [456, 2],
    [103, 1],
    [104, 0],
    [435, 2],
    [108, 1],
    [75, 1],
    [76, 0],
    [77, 2],
    [418, 2],
    [395, 1],
    [338, 1],
    [293, 1],
    [340, 3],
    [341, 2],
    [84, 3],
    [299, 0],
    [398, 0],
    [345, 0],
    [400, 1],
    [301, 2],
    [324, 1],
    [325, 0],
    [90, 2],
    [305, 0],
    [306, 1],
    [327, 2],
    [354, 1],
    [277, 2],
    [278, 0],
    [329, 3],
    [330, 2],
    [279, 1],
    [384, 1],
    [255, 2],
    [256, 0],
    [257, 2],
    [236, 2],
    [215, 2],
    [216, 0],
    [217, 1],
    [194, 2],
    [225, 3],
    [268, 3],
    [269, 1],
    [270, 3],
    [271, 1],
    [226, 2],
    [227, 0],
    [376, 3],
    [203, 0],
    [378, 1],
    [379, 0],
    [380, 1],
    [207, 2],
    [208, 0],
    [209, 1],
    [230, 1],
    [231, 0],
    [232, 1],
    [213, 0],
    [214, 1],
    [173, 0],
    [224, 3],
    [267, 0],
    [272, 1],
    [373, 0],
    [374, 2],
    [375, 3],
    [274, 0],
    [275, 1],
    [182, 2],
    [377, 2],
    [228, 1],
    [229, 3],
    [186, 0],
    [187, 2],
    [188, 3],
    [233, 2],
    [234, 0],
    [235, 2],
    [192, 2],
    [193, 3],
    [170, 0],
    [171, 2],
    [172, 3],
    [237, 0],
    [238, 1],
    [239, 0],
    [240, 1],
    [241, 0],
    [242, 1],
    [195, 1],
    [174, 1],
    [179, 0],
    [180, 2],
    [205, 3],
    [206, 1],
    [189, 3],
    [190, 2],
    [191, 3],
    [210, 0],
    [211, 2],
    [212, 0],
    [169, 0],
    [218, 2],
    [219, 3],
    [220, 2],
    [221, 3],
    [222, 2],
    [223, 3],
    [266, 3],
    [369, 0],
    [370, 1],
    [371, 0],
    [350, 0],
    [351, 1],
    [352, 0],
    [353, 1],
    [276, 2],
    [381, 2],
    [382, 3],
    [383, 2],
    [166, 0],
    [167, 2],
    [168, 0],
    [361, 0],
    [362, 1],
    [363, 3],
    [364, 1],
    [365, 3],
    [366, 2],
    [367, 0],
    [368, 2],
    [243, 1],
    [196, 2],
    [175, 1],
    [176, 3],
    [177, 1],
    [178, 3],
    [197, 3],
    [372, 0],
    [201, 2],
    [202, 3],
    [251, 0],
    [160, 0],
    [161, 2],
    [164, 3],
    [385, 2],
    [358, 0],
    [359, 2],
    [360, 3],
    [315, 3],
    [316, 2],
    [317, 3],
    [334, 3],
    [335, 1],
    [336, 0],
    [337, 2],
    [318, 2],
    [319, 3],
    [144, 3],
    [339, 3],
    [80, 0],
    [343, 1],
    [82, 1],
    [83, 3],
    [148, 2],
    [347, 0],
    [152, 0],
    [401, 0],
    [402, 1],
    [91, 1],
    [156, 2],
    [157, 3],
    [406, 0],
    [95, 0],
    [96, 2],
    [97, 0],
    [98, 2],
    [407, 2],
    [388, 2],
    [333, 1],
    [284, 1],
    [285, 0],
    [286, 1],
    [291, 0],
    [292, 1],
    [85, 3],
    [348, 3],
    [87, 2],
    [88, 3],
    [153, 3],
    [154, 2],
    [89, 1],
    [158, 0],
    [355, 2],
    [162, 1],
    [163, 0],
    [356, 3],
    [387, 2],
    [314, 3],
    [287, 1],
    [288, 3],
    [289, 2],
    [290, 0],
    [143, 3],
    [294, 1],
    [145, 1],
    [146, 0],
    [81, 3],
    [296, 3],
    [397, 3],
    [150, 2],
    [399, 1],
    [300, 2],
    [321, 1],
    [86, 2],
    [247, 2],
    [248, 3],
    [249, 2],
    [250, 3],
    [159, 3],
    [328, 0],
    [331, 1],
    [386, 1],
    [281, 2],
    [282, 0],
    [283, 1],
    [258, 2],
    [259, 3],
    [260, 1],
    [261, 3],
    [262, 1],
    [263, 0],
    [264, 2],
    [265, 0],
    [244, 2],
    [245, 3],
    [246, 2],
    [273, 2],
    [198, 2],
    [199, 0],
    [200, 1],
    [181, 1],
    [204, 0],
    [183, 3],
    [184, 2],
    [185, 3],
    [252, 0],
    [253, 1],
    [254, 0],
    [165, 3],
    [280, 0],
    [357, 3],
    [332, 0],
    [313, 0],
    [412, 0],
    [413, 1],
    [414, 3],
    [415, 1],
    [416, 3],
    [417, 1],
    [142, 3],
    [79, 0],
    [344, 1],
    [149, 2],
    [346, 3],
    [151, 3],
    [302, 2],
    [303, 3],
    [92, 2],
    [93, 3],
    [94, 1],
    [307, 2],
    [312, 0],
    [71, 3],
    [100, 3],
    [101, 2],
    [72, 1],
    [389, 2],
    [390, 3],
    [391, 1],
    [392, 3],
    [393, 1],
    [394, 3],
    [141, 0],
    [78, 0],
    [441, 0],
    [32, 3],
    [63, 3],
    [468, 0],
    [469, 2],
    [64, 2],
    [443, 1],
    [34, 2],
    [67, 0],
    [68, 1],
    [69, 3],
    [40, 3],
    [41, 2],
    [102, 2],
    [105, 0],
    [136, 0],
    [109, 2],
    [110, 0],
    [111, 2],
    [462, 0],
    [463, 1],
    [420, 2],
    [33, 0],
    [426, 3],
    [65, 0],
    [470, 0],
    [7, 3],
    [8, 2],
    [9, 3],
    [10, 1],
    [127, 3],
    [12, 3],
    [13, 2],
    [44, 1],
    [479, 2],
    [132, 2],
    [133, 0],
    [50, 3],
    [51, 2],
    [52, 0],
    [53, 2],
    [112, 1],
    [439, 2],
    [440, 3],
    [27, 3],
    [28, 1],
    [31, 3],
    [62, 0],
    [423, 2],
    [424, 0],
    [445, 2],
    [36, 1],
    [37, 3],
    [38, 1],
    [39, 3],
    [42, 2],
    [129, 3],
    [130, 2],
    [131, 0],
    [454, 0],
    [49, 3],
    [18, 0],
    [23, 1],
    [24, 0]
  ]
}