{
  "n_strands": 19,
  "n_strand_crossings": 231,
  "n_components": 1,
  "n_crossings": 236,
  "n_conn_visits": [
    472
  ],
  "visits": [
    [451, 2],
    [452, 0],
    [33, 2],
    [34, 3],
    [221, 1],
    [456, 1],
    [223, 3],
    [38, 1],
    [225, 1],
    [226, 3],
    [227, 1],
    [228, 3],
    [433, 2],
    [434, 3],
    [435, 1],
    [230, 2],
    [411, 2],
    [236, 3],
    [415, 3],
    [240, 2],
    [241, 3],
    [46, 3],
    [419, 2],
    [48, 1],
    [243, 1],
    [208, 2],
    [71, 1],
    [72, 0],
    [423, 0],
    [54, 0],
    [247, 0],
    [218, 3],
    [453, 3],
    [2, 0],
    [3, 1],
    [454, 2],
    [219, 1],
    [224, 3],
    [7, 3],
    [458, 3],
    [459, 2],
    [460, 0],
    [463, 1],
    [440, 1],
    [441, 0],
    [442, 2],
    [21, 1],
    [418, 1],
    [23, 3],
    [420, 0],
    [467, 3],
    [468, 2],
    [211, 2],
    [246, 2],
    [29, 2],
    [248, 0],
    [255, 1],
    [426, 1],
    [405, 1],
    [406, 3],
    [407, 2],
    [174, 1],
    [261, 3],
    [176, 3],
    [177, 1],
    [264, 2],
    [265, 0],
    [178, 3],
    [179, 1],
    [206, 1],
    [183, 3],
    [26, 3],
    [27, 2],
    [188, 1],
    [373, 2],
    [402, 2],
    [103, 1],
    [170, 2],
    [387, 0],
    [388, 2],
    [113, 0],
    [390, 3],
    [201, 3],
    [392, 2],
    [203, 2],
    [394, 3],
    [267, 3],
    [396, 2],
    [397, 0],
    [398, 1],
    [367, 1],
    [272, 2],
    [273, 3],
    [368, 0],
    [369, 1],
    [158, 1],
    [159, 0],
    [348, 1],
    [305, 1],
    [308, 0],
    [351, 0],
    [352, 2],
    [353, 3],
    [76, 3],
    [191, 3],
    [192, 2],
    [193, 3],
    [380, 0],
    [383, 1],
    [384, 3],
    [173, 1],
    [198, 1],
    [389, 1],
    [80, 2],
    [151, 2],
    [152, 0],
    [153, 1],
    [364, 1],
    [343, 2],
    [344, 3],
    [345, 2],
    [302, 1],
    [281, 0],
    [284, 1],
    [313, 3],
    [146, 1],
    [335, 2],
    [316, 2],
    [337, 0],
    [292, 0],
    [293, 1],
    [294, 3],
    [295, 1],
    [338, 2],
    [339, 0],
    [320, 3],
    [341, 1],
    [322, 2],
    [323, 3],
    [324, 1],
    [327, 3],
    [328, 1],
    [331, 3],
    [332, 1],
    [315, 3],
    [334, 0],
    [125, 3],
    [290, 0],
    [297, 1],
    [298, 3],
    [363, 0],
    [114, 0],
    [115, 2],
    [116, 3],
    [269, 0],
    [366, 1],
    [271, 2],
    [274, 3],
    [95, 3],
    [96, 2],
    [347, 1],
    [304, 1],
    [277, 2],
    [278, 0],
    [279, 2],
    [280, 3],
    [309, 0],
    [354, 0],
    [355, 1],
    [356, 3],
    [77, 0],
    [386, 3],
    [197, 3],
    [110, 3],
    [61, 3],
    [260, 0],
    [63, 1],
    [64, 3],
    [67, 1],
    [68, 3],
    [237, 3],
    [238, 1],
    [207, 2],
    [70, 1],
    [399, 1],
    [370, 1],
    [401, 3],
    [372, 3],
    [73, 3],
    [374, 2],
    [403, 1],
    [104, 1],
    [105, 0],
    [106, 1],
    [381, 0],
    [382, 1],
    [385, 3],
    [172, 1],
    [111, 3],
    [262, 3],
    [263, 1],
    [82, 1],
    [391, 1],
    [84, 0],
    [393, 0],
    [266, 3],
    [69, 3],
    [182, 0],
    [25, 0],
    [244, 3],
    [421, 3],
    [52, 0],
    [447, 0],
    [470, 3],
    [471, 1],
    [448, 2],
    [449, 3],
    [450, 1],
    [31, 1],
    [36, 3],
    [455, 0],
    [4, 3],
    [457, 2],
    [6, 1],
    [37, 1],
    [8, 3],
    [9, 1],
    [10, 3],
    [11, 1],
    [432, 1],
    [15, 0],
    [438, 3],
    [439, 1],
    [412, 1],
    [413, 3],
    [414, 2],
    [17, 1],
    [180, 1],
    [181, 3],
    [416, 3],
    [19, 0],
    [20, 1],
    [417, 2],
    [24, 3],
    [209, 1],
    [422, 3],
    [53, 0],
    [30, 2],
    [55, 2],
    [424, 1],
    [375, 2],
    [376, 0],
    [377, 1],
    [378, 0],
    [425, 0],
    [56, 3],
    [427, 1],
    [428, 3],
    [431, 1],
    [410, 2],
    [175, 2],
    [62, 1],
    [199, 1],
    [200, 3],
    [65, 0],
    [66, 2],
    [205, 1],
    [86, 1],
    [395, 2],
    [154, 2],
    [365, 1],
    [156, 0],
    [91, 0],
    [92, 1],
    [157, 1],
    [346, 1],
    [303, 2],
    [162, 0],
    [163, 2],
    [164, 0],
    [165, 1],
    [122, 2],
    [329, 1],
    [330, 3],
    [123, 3],
    [358, 3],
    [311, 0],
    [360, 1],
    [361, 3],
    [362, 1],
    [147, 2],
    [318, 2],
    [129, 2],
    [130, 3],
    [131, 1],
    [132, 3],
    [319, 3],
    [148, 3],
    [149, 1],
    [342, 2],
    [325, 2],
    [326, 3],
    [121, 3],
    [276, 0],
    [161, 3],
    [98, 3],
    [349, 0],
    [350, 2],
    [99, 2],
    [166, 2],
    [357, 0],
    [286, 2],
    [359, 1],
    [124, 1],
    [333, 2],
    [144, 1],
    [127, 0],
    [336, 0],
    [291, 0],
    [296, 1],
    [135, 1],
    [340, 1],
    [137, 0],
    [138, 1],
    [139, 3],
    [300, 0],
    [301, 1],
    [140, 1],
    [141, 3],
    [282, 3],
    [283, 1],
    [142, 1],
    [143, 3],
    [314, 0],
    [145, 2],
    [126, 0],
    [317, 2],
    [128, 2],
    [133, 0],
    [134, 2],
    [321, 3],
    [136, 3],
    [299, 0],
    [118, 0],
    [119, 1],
    [120, 0],
    [275, 3],
    [160, 3],
    [97, 3],
    [306, 2],
    [307, 0],
    [100, 2],
    [101, 0],
    [102, 1],
    [167, 2],
    [168, 3],
    [169, 1],
    [310, 2],
    [285, 1],
    [312, 3],
    [287, 3],
    [288, 1],
    [289, 3],
    [150, 2],
    [117, 3],
    [270, 3],
    [155, 3],
    [90, 3],
    [93, 2],
    [94, 3],
    [185, 3],
    [400, 3],
    [187, 1],
    [74, 0],
    [189, 0],
    [250, 0],
    [251, 2],
    [252, 3],
    [253, 2],
    [404, 2],
    [107, 2],
    [194, 2],
    [195, 3],
    [108, 3],
    [109, 1],
    [196, 1],
    [171, 1],
    [78, 2],
    [79, 0],
    [112, 3],
    [81, 1],
    [202, 3],
    [83, 0],
    [204, 2],
    [85, 1],
    [268, 0],
    [87, 0],
    [88, 2],
    [89, 3],
    [184, 3],
    [371, 1],
    [186, 1],
    [75, 0],
    [190, 3],
    [379, 0],
    [58, 3],
    [59, 1],
    [60, 0],
    [429, 0],
    [430, 2],
    [259, 0],
    [16, 0],
    [233, 3],
    [234, 1],
    [235, 0],
    [18, 1],
    [239, 1],
    [242, 0],
    [47, 3],
    [22, 0],
    [49, 2],
    [210, 1],
    [245, 1],
    [28, 2],
    [249, 3],
    [254, 2],
    [57, 3],
    [256, 3],
    [257, 1],
    [408, 2],
    [409, 0],
    [258, 3],
    [229, 3],
    [12, 0],
    [13, 1],
    [14, 3],
    [461, 0],
    [462, 2],
    [231, 1],
    [232, 3],
    [43, 3],
    [44, 2],
    [45, 0],
    [464, 0],
    [465, 2],
    [466, 3],
    [469, 1],
    [212, 2],
    [215, 0],
    [216, 1],
    [217, 3],
    [0, 0],
    [1, 2],
    [32, 1],
    [35, 0],
    [220, 2],
    [5, 3],
    [222, 0],
    [39, 1],
    [40, 0],
    [41, 2],
    [436, 2],
    [437, 0],
    [42, 3],
    [443, 2],
    [444, 0],
    [445, 1],
    [50, 1],
    [51, 0],
    [446, 3],
    [213, 1],
    [214, 3]
  ]
}