{
  "n_strands": 4,
  "n_strand_crossings": 87,
  "n_components": 1,
  "n_crossings": 87,
  "n_conn_visits": [
    174
  ],
  "visits": [
    [127, 1],
    [128, 0],
    [91, 2],
    [92, 3],
    [93, 2],
    [130, 2],
    [131, 3],
    [94, 3],
    [95, 1],
    [54, 2],
    [137, 2],
    [138, 0],
    [97, 3],
    [56, 3],
    [57, 1],
    [98, 1],
    [139, 1],
    [140, 3],
    [141, 2],
    [142, 3],
    [59, 0],
    [100, 0],
    [63, 2],
    [64, 0],
    [153, 1],
    [154, 0],
    [155, 2],
    [156, 3],
    [75, 1],
    [160, 2],
    [161, 3],
    [76, 3],
    [79, 2],
    [164, 1],
    [165, 0],
    [112, 1],
    [115, 0],
    [82, 0],
    [169, 1],
    [170, 3],
    [171, 1],
    [118, 1],
    [119, 0],
    [120, 2],
    [85, 1],
    [88, 0],
    [125, 0],
    [126, 1],
    [89, 1],
    [132, 3],
    [133, 2],
    [134, 0],
    [135, 2],
    [136, 3],
    [9, 0],
    [96, 0],
    [13, 1],
    [14, 3],
    [99, 1],
    [20, 2],
    [143, 1],
    [102, 0],
    [145, 0],
    [22, 0],
    [23, 2],
    [146, 2],
    [147, 3],
    [150, 1],
    [151, 0],
    [152, 1],
    [105, 2],
    [106, 0],
    [107, 1],
    [158, 3],
    [109, 3],
    [28, 3],
    [31, 1],
    [162, 1],
    [163, 3],
    [32, 0],
    [113, 1],
    [114, 0],
    [37, 2],
    [168, 1],
    [117, 2],
    [44, 3],
    [123, 0],
    [124, 2],
    [45, 2],
    [48, 3],
    [129, 0],
    [2, 0],
    [3, 1],
    [4, 0],
    [7, 1],
    [8, 3],
    [55, 2],
    [12, 1],
    [15, 3],
    [58, 3],
    [21, 2],
    [144, 2],
    [61, 2],
    [148, 3],
    [149, 2],
    [70, 0],
    [71, 2],
    [72, 3],
    [157, 3],
    [74, 1],
    [159, 1],
    [166, 3],
    [35, 3],
    [80, 3],
    [81, 2],
    [36, 2],
    [167, 2],
    [84, 0],
    [41, 3],
    [42, 2],
    [43, 0],
    [172, 3],
    [173, 2],
    [86, 2],
    [87, 0],
    [46, 2],
    [47, 3],
    [0, 3],
    [1, 2],
    [90, 2],
    [5, 0],
    [6, 1],
    [49, 1],
    [50, 0],
    [51, 2],
    [52, 0],
    [53, 1],
    [10, 0],
    [11, 2],
    [16, 3],
    [17, 1],
    [18, 0],
    [19, 1],
    [60, 3],
    [101, 0],
    [62, 2],
    [65, 0],
    [66, 1],
    [103, 1],
    [104, 0],
    [67, 3],
    [68, 2],
    [69, 3],
    [24, 3],
    [25, 2],
    [26, 0],
    [27, 1],
    [108, 1],
    [73, 1],
    [110, 3],
    [29, 0],
    [30, 1],
    [77, 3],
    [78, 1],
    [33, 3],
    [34, 2],
    [111, 1],
    [116, 0],
    [83, 3],
    [38, 3],
    [39, 1],
    [40, 3],
    [121, 1],
    [122, 0]
  ]
}